{
    "timestamp": "20250927_005149",
    "image_filename": "webcam_captures/images/capture_20250927_005149.jpg",
    "detected_persons": 1,
    "persons": [
        {
            "person_id": 1,
            "keypoints": [
                {
                    "part_id": 0,
                    "part_name": "nose",
                    "x": 255.44927978515625,
                    "y": 115.22210693359375,
                    "confidence": 0.9762594699859619
                },
                {
                    "part_id": 1,
                    "part_name": "left_eye",
                    "x": 261.37646484375,
                    "y": 102.89830017089844,
                    "confidence": 0.9906992316246033
                },
                {
                    "part_id": 2,
                    "part_name": "right_eye",
                    "x": 253.43923950195312,
                    "y": 106.7392578125,
                    "confidence": 0.36123090982437134
                },
                {
                    "part_id": 3,
                    "part_name": "left_ear",
                    "x": 295.0939025878906,
                    "y": 93.57403564453125,
                    "confidence": 0.9857479929924011
                },
                {
                    "part_id": 4,
                    "part_name": "right_ear",
                    "x": 276.2748107910156,
                    "y": 102.03904724121094,
                    "confidence": 0.015533487312495708
                },
                {
                    "part_id": 5,
                    "part_name": "left_shoulder",
                    "x": 317.9971618652344,
                    "y": 138.302001953125,
                    "confidence": 0.9968574047088623
                },
                {
                    "part_id": 6,
                    "part_name": "right_shoulder",
                    "x": 319.4784240722656,
                    "y": 139.88522338867188,
                    "confidence": 0.9086951017379761
                },
                {
                    "part_id": 7,
                    "part_name": "left_elbow",
                    "x": 252.06517028808594,
                    "y": 211.93496704101562,
                    "confidence": 0.9961940050125122
                },
                {
                    "part_id": 8,
                    "part_name": "right_elbow",
                    "x": 276.7904052734375,
                    "y": 208.56924438476562,
                    "confidence": 0.615145742893219
                },
                {
                    "part_id": 9,
                    "part_name": "left_wrist",
                    "x": 208.88153076171875,
                    "y": 193.7611541748047,
                    "confidence": 0.9933307766914368
                },
                {
                    "part_id": 10,
                    "part_name": "right_wrist",
                    "x": 225.75,
                    "y": 194.31385803222656,
                    "confidence": 0.7590553164482117
                },
                {
                    "part_id": 11,
                    "part_name": "left_hip",
                    "x": 352.0537109375,
                    "y": 286.59393310546875,
                    "confidence": 0.9925023317337036
                },
                {
                    "part_id": 12,
                    "part_name": "right_hip",
                    "x": 350.3530578613281,
                    "y": 278.69964599609375,
                    "confidence": 0.9650819301605225
                },
                {
                    "part_id": 13,
                    "part_name": "left_knee",
                    "x": 214.64158630371094,
                    "y": 278.7215881347656,
                    "confidence": 0.996099591255188
                },
                {
                    "part_id": 14,
                    "part_name": "right_knee",
                    "x": 225.11846923828125,
                    "y": 273.770751953125,
                    "confidence": 0.9766853451728821
                },
                {
                    "part_id": 15,
                    "part_name": "left_ankle",
                    "x": 183.6430206298828,
                    "y": 421.5664367675781,
                    "confidence": 0.9784473776817322
                },
                {
                    "part_id": 16,
                    "part_name": "right_ankle",
                    "x": 190.6945037841797,
                    "y": 410.83184814453125,
                    "confidence": 0.9403010606765747
                }
            ]
        }
    ]
}