{
    "timestamp": "20250927_003403",
    "image_filename": "webcam_captures/images/capture_20250927_003403.jpg",
    "detected_persons": 1,
    "persons": [
        {
            "person_id": 1,
            "keypoints": [
                {
                    "part_id": 0,
                    "part_name": "nose",
                    "x": 264.7811584472656,
                    "y": 105.0684814453125,
                    "confidence": 0.9173550009727478
                },
                {
                    "part_id": 1,
                    "part_name": "left_eye",
                    "x": 266.7301330566406,
                    "y": 90.26017761230469,
                    "confidence": 0.9706364274024963
                },
                {
                    "part_id": 2,
                    "part_name": "right_eye",
                    "x": 267.6969299316406,
                    "y": 96.07113647460938,
                    "confidence": 0.11538071185350418
                },
                {
                    "part_id": 3,
                    "part_name": "left_ear",
                    "x": 297.7296142578125,
                    "y": 84.04472351074219,
                    "confidence": 0.9911080598831177
                },
                {
                    "part_id": 4,
                    "part_name": "right_ear",
                    "x": 310.83929443359375,
                    "y": 95.24687194824219,
                    "confidence": 0.03186323866248131
                },
                {
                    "part_id": 5,
                    "part_name": "left_shoulder",
                    "x": 297.98724365234375,
                    "y": 142.22885131835938,
                    "confidence": 0.9970486760139465
                },
                {
                    "part_id": 6,
                    "part_name": "right_shoulder",
                    "x": 361.15826416015625,
                    "y": 140.31593322753906,
                    "confidence": 0.9292578101158142
                },
                {
                    "part_id": 7,
                    "part_name": "left_elbow",
                    "x": 220.0968017578125,
                    "y": 222.730224609375,
                    "confidence": 0.9939388036727905
                },
                {
                    "part_id": 8,
                    "part_name": "right_elbow",
                    "x": 322.19549560546875,
                    "y": 226.48509216308594,
                    "confidence": 0.5003694295883179
                },
                {
                    "part_id": 9,
                    "part_name": "left_wrist",
                    "x": 214.29156494140625,
                    "y": 209.276123046875,
                    "confidence": 0.9843302369117737
                },
                {
                    "part_id": 10,
                    "part_name": "right_wrist",
                    "x": 269.43743896484375,
                    "y": 236.65927124023438,
                    "confidence": 0.5580170750617981
                },
                {
                    "part_id": 11,
                    "part_name": "left_hip",
                    "x": 296.15997314453125,
                    "y": 302.4980163574219,
                    "confidence": 0.9888648986816406
                },
                {
                    "part_id": 12,
                    "part_name": "right_hip",
                    "x": 336.3267822265625,
                    "y": 292.5201416015625,
                    "confidence": 0.9466029405593872
                },
                {
                    "part_id": 13,
                    "part_name": "left_knee",
                    "x": 162.14544677734375,
                    "y": 281.3694152832031,
                    "confidence": 0.992820680141449
                },
                {
                    "part_id": 14,
                    "part_name": "right_knee",
                    "x": 205.86587524414062,
                    "y": 272.53314208984375,
                    "confidence": 0.9556363224983215
                },
                {
                    "part_id": 15,
                    "part_name": "left_ankle",
                    "x": 144.68106079101562,
                    "y": 426.6299743652344,
                    "confidence": 0.9599695205688477
                },
                {
                    "part_id": 16,
                    "part_name": "right_ankle",
                    "x": 159.72999572753906,
                    "y": 405.61834716796875,
                    "confidence": 0.8855966329574585
                }
            ]
        }
    ]
}