{
    "timestamp": "20250927_004551",
    "image_filename": "webcam_captures/images/capture_20250927_004551.jpg",
    "detected_persons": 1,
    "persons": [
        {
            "person_id": 1,
            "keypoints": [
                {
                    "part_id": 0,
                    "part_name": "nose",
                    "x": 368.94232177734375,
                    "y": 60.036285400390625,
                    "confidence": 0.955544114112854
                },
                {
                    "part_id": 1,
                    "part_name": "left_eye",
                    "x": 376.1171875,
                    "y": 47.457366943359375,
                    "confidence": 0.9749959707260132
                },
                {
                    "part_id": 2,
                    "part_name": "right_eye",
                    "x": 366.40435791015625,
                    "y": 50.46051025390625,
                    "confidence": 0.37619221210479736
                },
                {
                    "part_id": 3,
                    "part_name": "left_ear",
                    "x": 401.4206848144531,
                    "y": 51.744049072265625,
                    "confidence": 0.9662137627601624
                },
                {
                    "part_id": 4,
                    "part_name": "right_ear",
                    "x": 385.0403137207031,
                    "y": 57.636260986328125,
                    "confidence": 0.04835544526576996
                },
                {
                    "part_id": 5,
                    "part_name": "left_shoulder",
                    "x": 412.9952392578125,
                    "y": 116.56341552734375,
                    "confidence": 0.9858624339103699
                },
                {
                    "part_id": 6,
                    "part_name": "right_shoulder",
                    "x": 410.87347412109375,
                    "y": 113.22550964355469,
                    "confidence": 0.9181402921676636
                },
                {
                    "part_id": 7,
                    "part_name": "left_elbow",
                    "x": 349.6333312988281,
                    "y": 209.621826171875,
                    "confidence": 0.9796604514122009
                },
                {
                    "part_id": 8,
                    "part_name": "right_elbow",
                    "x": 366.1099853515625,
                    "y": 192.38955688476562,
                    "confidence": 0.6395741105079651
                },
                {
                    "part_id": 9,
                    "part_name": "left_wrist",
                    "x": 269.18890380859375,
                    "y": 194.07571411132812,
                    "confidence": 0.9766395688056946
                },
                {
                    "part_id": 10,
                    "part_name": "right_wrist",
                    "x": 295.33477783203125,
                    "y": 185.716796875,
                    "confidence": 0.7494486570358276
                },
                {
                    "part_id": 11,
                    "part_name": "left_hip",
                    "x": 406.7091064453125,
                    "y": 277.4920959472656,
                    "confidence": 0.9532654285430908
                },
                {
                    "part_id": 12,
                    "part_name": "right_hip",
                    "x": 402.4337158203125,
                    "y": 266.60528564453125,
                    "confidence": 0.8908809423446655
                },
                {
                    "part_id": 13,
                    "part_name": "left_knee",
                    "x": 275.5148010253906,
                    "y": 287.8401794433594,
                    "confidence": 0.9750133156776428
                },
                {
                    "part_id": 14,
                    "part_name": "right_knee",
                    "x": 279.0871887207031,
                    "y": 281.17669677734375,
                    "confidence": 0.9204408526420593
                },
                {
                    "part_id": 15,
                    "part_name": "left_ankle",
                    "x": 258.8624267578125,
                    "y": 433.785888671875,
                    "confidence": 0.8738255500793457
                },
                {
                    "part_id": 16,
                    "part_name": "right_ankle",
                    "x": 256.9241943359375,
                    "y": 425.0647888183594,
                    "confidence": 0.7746862769126892
                }
            ]
        }
    ]
}