{
    "timestamp": "20250927_001458",
    "image_filename": "capture_20250927_001458.jpg",
    "image_path": "webcam_captures/images/capture_20250927_001458.jpg",
    "models_used": [
        "YOLOv8_fallback"
    ],
    "total_detections": 1,
    "yolo_nas_results": [
        {
            "model": "YOLOv8_fallback",
            "person_id": 1,
            "keypoints": [
                {
                    "part_id": 0,
                    "x": 260.0487060546875,
                    "y": 107.23959350585938,
                    "confidence": 0.9597209692001343
                },
                {
                    "part_id": 1,
                    "x": 265.2738342285156,
                    "y": 95.36459350585938,
                    "confidence": 0.9870105981826782
                },
                {
                    "part_id": 2,
                    "x": 260.9140319824219,
                    "y": 100.00529479980469,
                    "confidence": 0.27544063329696655
                },
                {
                    "part_id": 3,
                    "x": 297.7507019042969,
                    "y": 88.76007080078125,
                    "confidence": 0.9892240166664124
                },
                {
                    "part_id": 4,
                    "x": 290.05462646484375,
                    "y": 95.88803100585938,
                    "confidence": 0.01978546567261219
                },
                {
                    "part_id": 5,
                    "x": 329.21484375,
                    "y": 136.2906494140625,
                    "confidence": 0.9965529441833496
                },
                {
                    "part_id": 6,
                    "x": 332.215576171875,
                    "y": 131.58383178710938,
                    "confidence": 0.902633786201477
                },
                {
                    "part_id": 7,
                    "x": 278.5341491699219,
                    "y": 208.20846557617188,
                    "confidence": 0.9942150712013245
                },
                {
                    "part_id": 8,
                    "x": 293.0144958496094,
                    "y": 190.34674072265625,
                    "confidence": 0.5173996686935425
                },
                {
                    "part_id": 9,
                    "x": 231.26260375976562,
                    "y": 188.65499877929688,
                    "confidence": 0.9861837029457092
                },
                {
                    "part_id": 10,
                    "x": 240.62548828125,
                    "y": 186.46458435058594,
                    "confidence": 0.6134679913520813
                },
                {
                    "part_id": 11,
                    "x": 375.62298583984375,
                    "y": 278.0081481933594,
                    "confidence": 0.9900553226470947
                },
                {
                    "part_id": 12,
                    "x": 375.3926086425781,
                    "y": 267.7950439453125,
                    "confidence": 0.9570120573043823
                },
                {
                    "part_id": 13,
                    "x": 227.3622283935547,
                    "y": 305.0101013183594,
                    "confidence": 0.9932142496109009
                },
                {
                    "part_id": 14,
                    "x": 236.78903198242188,
                    "y": 289.8318176269531,
                    "confidence": 0.9610540270805359
                },
                {
                    "part_id": 15,
                    "x": 252.49655151367188,
                    "y": 440.56695556640625,
                    "confidence": 0.9578804969787598
                },
                {
                    "part_id": 16,
                    "x": 249.37942504882812,
                    "y": 411.5280456542969,
                    "confidence": 0.8952354788780212
                }
            ]
        }
    ],
    "hrnet_results": []
}