{
    "timestamp": "20250927_004449",
    "image_filename": "capture_20250927_004449.jpg",
    "image_path": "webcam_captures/images/capture_20250927_004449.jpg",
    "models_used": [
        "YOLOv8_fallback"
    ],
    "total_detections": 1,
    "yolo_nas_results": [
        {
            "model": "YOLOv8_fallback",
            "person_id": 1,
            "keypoints": [
                {
                    "part_id": 0,
                    "x": 516.1493530273438,
                    "y": 72.15879821777344,
                    "confidence": 0.9420815706253052
                },
                {
                    "part_id": 1,
                    "x": 526.9423828125,
                    "y": 64.09461975097656,
                    "confidence": 0.943282425403595
                },
                {
                    "part_id": 2,
                    "x": 519.15673828125,
                    "y": 63.27070617675781,
                    "confidence": 0.3182268738746643
                },
                {
                    "part_id": 3,
                    "x": 559.178955078125,
                    "y": 77.96992492675781,
                    "confidence": 0.9184955358505249
                },
                {
                    "part_id": 4,
                    "x": 538.5042114257812,
                    "y": 76.08290100097656,
                    "confidence": 0.03232806921005249
                },
                {
                    "part_id": 5,
                    "x": 550.9547119140625,
                    "y": 140.48519897460938,
                    "confidence": 0.9886690974235535
                },
                {
                    "part_id": 6,
                    "x": 538.12646484375,
                    "y": 132.2974090576172,
                    "confidence": 0.971060037612915
                },
                {
                    "part_id": 7,
                    "x": 460.91558837890625,
                    "y": 213.08453369140625,
                    "confidence": 0.9888890981674194
                },
                {
                    "part_id": 8,
                    "x": 460.9749755859375,
                    "y": 207.44052124023438,
                    "confidence": 0.9106490612030029
                },
                {
                    "part_id": 9,
                    "x": 363.8747253417969,
                    "y": 173.13368225097656,
                    "confidence": 0.9886071085929871
                },
                {
                    "part_id": 10,
                    "x": 384.8743591308594,
                    "y": 173.57199096679688,
                    "confidence": 0.9131810665130615
                },
                {
                    "part_id": 11,
                    "x": 452.76837158203125,
                    "y": 282.9584655761719,
                    "confidence": 0.993157684803009
                },
                {
                    "part_id": 12,
                    "x": 442.5877685546875,
                    "y": 260.4498291015625,
                    "confidence": 0.9869694709777832
                },
                {
                    "part_id": 13,
                    "x": 280.46368408203125,
                    "y": 289.40411376953125,
                    "confidence": 0.9922107458114624
                },
                {
                    "part_id": 14,
                    "x": 278.3656005859375,
                    "y": 269.537841796875,
                    "confidence": 0.979526698589325
                },
                {
                    "part_id": 15,
                    "x": 196.62022399902344,
                    "y": 440.63555908203125,
                    "confidence": 0.9099864363670349
                },
                {
                    "part_id": 16,
                    "x": 208.3074493408203,
                    "y": 422.9778137207031,
                    "confidence": 0.8400416374206543
                }
            ]
        }
    ],
    "hrnet_results": []
}