{
    "timestamp": "20250927_002153",
    "image_filename": "capture_20250927_002153.jpg",
    "image_path": "webcam_captures/images/capture_20250927_002153.jpg",
    "models_used": [
        "YOLOv8_fallback"
    ],
    "total_detections": 1,
    "yolo_nas_results": [
        {
            "model": "YOLOv8_fallback",
            "person_id": 1,
            "keypoints": [
                {
                    "part_id": 0,
                    "x": 288.38262939453125,
                    "y": 67.30630493164062,
                    "confidence": 0.9808775186538696
                },
                {
                    "part_id": 1,
                    "x": 299.05865478515625,
                    "y": 56.00238037109375,
                    "confidence": 0.9832397103309631
                },
                {
                    "part_id": 2,
                    "x": 285.93670654296875,
                    "y": 57.08795166015625,
                    "confidence": 0.6322416663169861
                },
                {
                    "part_id": 3,
                    "x": 327.95233154296875,
                    "y": 58.10858154296875,
                    "confidence": 0.9624647498130798
                },
                {
                    "part_id": 4,
                    "x": 296.691162109375,
                    "y": 59.87689208984375,
                    "confidence": 0.061341069638729095
                },
                {
                    "part_id": 5,
                    "x": 345.6562194824219,
                    "y": 118.57279968261719,
                    "confidence": 0.9951317310333252
                },
                {
                    "part_id": 6,
                    "x": 307.2822570800781,
                    "y": 109.59445190429688,
                    "confidence": 0.974414050579071
                },
                {
                    "part_id": 7,
                    "x": 311.670166015625,
                    "y": 214.1351318359375,
                    "confidence": 0.9930100440979004
                },
                {
                    "part_id": 8,
                    "x": 267.2897033691406,
                    "y": 184.78250122070312,
                    "confidence": 0.8919376134872437
                },
                {
                    "part_id": 9,
                    "x": 220.07269287109375,
                    "y": 194.22244262695312,
                    "confidence": 0.9924620985984802
                },
                {
                    "part_id": 10,
                    "x": 219.54449462890625,
                    "y": 174.82321166992188,
                    "confidence": 0.9130145907402039
                },
                {
                    "part_id": 11,
                    "x": 307.4669189453125,
                    "y": 265.656005859375,
                    "confidence": 0.9930354952812195
                },
                {
                    "part_id": 12,
                    "x": 282.00506591796875,
                    "y": 249.69461059570312,
                    "confidence": 0.9838308095932007
                },
                {
                    "part_id": 13,
                    "x": 171.59036254882812,
                    "y": 291.0455627441406,
                    "confidence": 0.9940847754478455
                },
                {
                    "part_id": 14,
                    "x": 159.77349853515625,
                    "y": 280.021484375,
                    "confidence": 0.9822158813476562
                },
                {
                    "part_id": 15,
                    "x": 142.10018920898438,
                    "y": 437.94195556640625,
                    "confidence": 0.9472177624702454
                },
                {
                    "part_id": 16,
                    "x": 145.66943359375,
                    "y": 430.29583740234375,
                    "confidence": 0.9008268713951111
                }
            ]
        }
    ],
    "hrnet_results": []
}